cfcrawler/__init__.py
cfcrawler/cipher.py
cfcrawler/client.py
cfcrawler/py.typed
cfcrawler/tls.py
cfcrawler/types.py
cfcrawler/user_agent.py
cfcrawler-0.1.0.dist-info/LICENSE
cfcrawler-0.1.0.dist-info/METADATA
cfcrawler-0.1.0.dist-info/WHEEL
cfcrawler-0.1.0.dist-info/top_level.txt
cfcrawler-0.1.0.dist-info/RECORD
