Metadata-Version: 2.1
Name: cfcrawler
Version: 0.1.0
Summary: Cloudflare scraper and cralwer written in Async
Author-email: Mani Mozaffar <mani.mozaffar@gmail.com>
Requires-Python: >=3.9
License-File: LICENSE
Requires-Dist: httpx >=0.20
Requires-Dist: typing-extensions >=4.12.2
Provides-Extra: ua
Requires-Dist: fake-useragent >=1.5.1 ; extra == 'ua'
